setup.py
MaluubaOCR/__init__.py
MaluubaOCR/parser.py
MaluubaOCR.egg-info/PKG-INFO
MaluubaOCR.egg-info/SOURCES.txt
MaluubaOCR.egg-info/dependency_links.txt
MaluubaOCR.egg-info/requires.txt
MaluubaOCR.egg-info/top_level.txt