Metadata-Version: 1.1
Name: MaluubaOCR
Version: 0.1
Summary: Maluuba OCR
Home-page: http://maluuba.com
Author: Maluuba
Author-email: adrian.petrescu@maluuba.com
License: UNKNOWN
Download-URL: http://github.com/Maluuba/InterviewQuestions
Platform: UNKNOWN
